
    
    
    
    
    
    
    
    
    
    [{"authors":null,"categories":null,"content":"ご連絡はX (Twitter) まで． https://twitter.com/winter2enaga Tweets by winter2enaga ","date":1716681600,"expirydate":-62135596800,"kind":"term","lang":"ja","lastmod":1716681600,"objectID":"2525497d367e79493fd32b198b28f040","permalink":"","publishdate":"0001-01-01T00:00:00Z","relpermalink":"","section":"authors","summary":"ご連絡はX (Twitter) まで． https://twitter.com/winter2enaga Tweets by winter2enaga","tags":null,"title":"白岩 景","type":"authors"},{"authors":["白岩 景"],"categories":["学会"],"content":"今年度も参加いたします． よろしくお願いいたします．\nJpGU公式X Tweets by JpGU ","date":1716681600,"expirydate":-62135596800,"kind":"page","lang":"ja","lastmod":1716681600,"objectID":"7d211a1a88efc43684aeac1733417d82","permalink":"https://is-enaga.github.io/talk/jpgu-2024/","publishdate":"2024-02-06T00:00:00Z","relpermalink":"/talk/jpgu-2024/","section":"event","summary":"日本地球惑星科学連合2024年大会が開催されます．学部生以下は無料で参加可能です．","tags":["学会"],"title":"JpGU 2024","type":"event"},{"authors":null,"categories":null,"content":"","date":1709510400,"expirydate":-62135596800,"kind":"page","lang":"ja","lastmod":1709510400,"objectID":"30c3992696e79ca17a13117db67834fc","permalink":"https://is-enaga.github.io/links/eri/","publishdate":"2024-03-04T00:00:00Z","relpermalink":"/links/eri/","section":"links","summary":"ERI","tags":["Link"],"title":"東京大学地震研究所","type":"links"},{"authors":null,"categories":null,"content":"当サイトでは、Googleによるアクセス解析ツール「Googleアナリティクス」を使用しています。このGoogleアナリティクスはデータの収集のためにCookieを使用しています。このデータは匿名で収集されており、個人を特定するものではありません。\nこの機能はCookieを無効にすることで収集を拒否することが出来ますので、お使いのブラウザの設定をご確認ください。この規約に関しての詳細はGoogleアナリティクスサービス利用規約やGoogleポリシーと規約をご覧ください。\n","date":1709478000,"expirydate":-62135596800,"kind":"page","lang":"ja","lastmod":1709478000,"objectID":"18d05a63a1c8d7ed973cc51838494e41","permalink":"https://is-enaga.github.io/privacy/","publishdate":"2024-03-04T00:00:00+09:00","relpermalink":"/privacy/","section":"","summary":"当サイトでは、Googleによるアクセス解析ツール「Goog","tags":null,"title":"プライバシーポリシー　Privacy Policy","type":"page"},{"authors":["白岩 景"],"categories":["Projects"],"content":"Convert NumPy Data to WIN Format numpyのデータをWINフォーマットに書き出すモジュールのベータ版をGitHubに公開しました．\nhttps://github.com/is-enaga/winpy/blob/main/mkwin.py\nご自身のプログラムにimportやコピーペーストしてご利用ください． mkwin関数の引き数にnumpy.arrayとそのサンプリング周波数，データの開始日時を指定すると，numpy.arrayをWINに変換して出力します． ご意見・ご感想等ございましたらTwitterまでご連絡ください．\nA Python module to convert np.array data to WIN format is now uploaded on Github!\nhttps://github.com/is-enaga/winpy/blob/main/mkwin.py\nPlease use the “mkwin” function by providing its arguments: an np.array containing data, the sampling frequency, and the start time of the data. If you have any comments, please contact me through X (Twitter).\nExample 正弦波をWINフォーマットに変換した例を以下に示します．\nWINフォーマットは1秒区切りであるため，半端な秒数で開始・終了する場合に欠損部をなんらかの値で埋める必要があります． 現在はこの欠損部を端のデータ値で埋めるようにしています． (描画時のミスでPythonの波形の正負が逆になっていました．すみません．)\nInput (numpy) Output (WIN) 補足 WIN System by The University of Tokyo WINシステムは日本で用いられている地震波形の検測用ソフトおよびその周辺ツール． ダウンロードは以下から可能．\nhttps://wwweic.eri.u-tokyo.ac.jp/WIN/pub/win/\nWINフォーマットのデータはwintosacやwin2sacでSAC形式に変換可能． 一方で，他のフォーマットからWINフォーマットに変換するツールはほぼ公開されていないようだ．\nWIN system consists of a GUI picking tool and other surrounding commands. You can download WIN from:\nhttps://wwweic.eri.u-tokyo.ac.jp/WIN/pub/win/\nWIN format data can be converted to SAC with wintosac command or win2sac command. On the other hand, tools to obtain WIN data from other formats are not exist.\nRead WIN Format Data with Python WINデータの読み込みはobspyで可能． ただしそのときは，中川茂樹先生のモジュールを合わせて使うことを推奨する．\nWIN data can be read with obspy (https://docs.obspy.org/). Then you are recommended to use modifying patch by Nakagawa because original obspy code has some bugs on reading WIN data.\nhttps://www.eri.u-tokyo.ac.jp/people/nakagawa/win/\n","date":1708387200,"expirydate":-62135596800,"kind":"page","lang":"ja","lastmod":1709510400,"objectID":"9d652205a33bea97a790d6b361acb68e","permalink":"https://is-enaga.github.io/note/win/","publishdate":"2024-02-20T00:00:00Z","relpermalink":"/note/win/","section":"note","summary":"PythonでWINフォーマットを出力するモジュールを公開しています","tags":["Academic"],"title":"WINフォーマットファイルをPythonで作る","type":"note"},{"authors":["白岩 景"],"categories":["散策"],"content":"図書館周辺 ","date":1707177600,"expirydate":-62135596800,"kind":"page","lang":"ja","lastmod":1707177600,"objectID":"2ffca732092cc3081ef91d54e5500439","permalink":"https://is-enaga.github.io/post/todai_arch/","publishdate":"2024-02-06T00:00:00Z","relpermalink":"/post/todai_arch/","section":"post","summary":"東大本郷キャンパスのアーチを散策","tags":["Academic"],"title":"東大アーチ散策","type":"post"},{"authors":["白岩 景"],"categories":["学会"],"content":"","date":1698710400,"expirydate":-62135596800,"kind":"page","lang":"ja","lastmod":1698710400,"objectID":"21e22542d6e8ce9e64dfbade4e9f4991","permalink":"https://is-enaga.github.io/talk/ssj-2023/","publishdate":"2023-08-27T01:38:57+09:00","relpermalink":"/talk/ssj-2023/","section":"event","summary":"SSJ2023が横浜で開催されました．","tags":["学会"],"title":"SSJ 2023","type":"event"},{"authors":["白岩 景"],"categories":["学会"],"content":"","date":1684627200,"expirydate":-62135596800,"kind":"page","lang":"ja","lastmod":1684627200,"objectID":"3db104f5f04e5fe9c940b2c6796df361","permalink":"https://is-enaga.github.io/talk/jpgu-2023/","publishdate":"2023-06-01T00:00:00Z","relpermalink":"/talk/jpgu-2023/","section":"event","summary":"日本地球惑星科学連合2023年大会が開催されました","tags":["学会"],"title":"JpGU 2023","type":"event"},{"authors":null,"categories":null,"content":"","date":1666569600,"expirydate":-62135596800,"kind":"page","lang":"ja","lastmod":1666569600,"objectID":"0e2fc1990eb89f870229bb6b0aa51de1","permalink":"https://is-enaga.github.io/__index/","publishdate":"2022-10-24T00:00:00Z","relpermalink":"/__index/","section":"","summary":"","tags":null,"title":"","type":"landing"},{"authors":["白岩 景"],"categories":["学会"],"content":"","date":-62135596800,"expirydate":-62135596800,"kind":"page","lang":"ja","lastmod":-62135596800,"objectID":"e34c28dc5940c60df1dc5a523d1c67ac","permalink":"https://is-enaga.github.io/talk/%E5%9C%B0%E9%9C%87%E5%AD%A6%E5%A4%8F%E3%81%AE%E5%AD%A6%E6%A0%A1-2024/","publishdate":"0001-01-01T00:00:00Z","relpermalink":"/talk/%E5%9C%B0%E9%9C%87%E5%AD%A6%E5%A4%8F%E3%81%AE%E5%AD%A6%E6%A0%A1-2024/","section":"event","summary":"2024年も開催予定とのことです．編集時点で日付未定．","tags":["学会"],"title":"地震学夏の学校 2024","type":"event"}]